{
	"id": "1MgXOK8KMn1cQcx",
	"json": "{\"id\":\"1MgXOK8KMn1cQcx\",\"url\":\"https://support.squarespace.com/hc/sections/200825098\",\"uniqueKey\":\"https://support.squarespace.com/hc/sections/200825098\",\"method\":\"GET\",\"noRetry\":false,\"retryCount\":0,\"errorMessages\":[],\"headers\":{},\"userData\":{\"__crawlee\":{\"enqueueStrategy\":\"same-hostname\"}}}",
	"method": "GET",
	"orderNo": 1741581824689,
	"retryCount": 0,
	"uniqueKey": "https://support.squarespace.com/hc/sections/200825098",
	"url": "https://support.squarespace.com/hc/sections/200825098"
}