{
	"id": "5p3smk7K1lat8pz",
	"json": "{\"id\":\"5p3smk7K1lat8pz\",\"url\":\"https://www.ntu.edu.tw/spotlight/2017/1223_20170925.html\",\"uniqueKey\":\"https://www.ntu.edu.tw/spotlight/2017/1223_20170925.html\",\"method\":\"GET\",\"noRetry\":false,\"retryCount\":0,\"errorMessages\":[],\"headers\":{},\"userData\":{\"__crawlee\":{\"enqueueStrategy\":\"same-hostname\"}}}",
	"method": "GET",
	"orderNo": 1741478261924,
	"retryCount": 0,
	"uniqueKey": "https://www.ntu.edu.tw/spotlight/2017/1223_20170925.html",
	"url": "https://www.ntu.edu.tw/spotlight/2017/1223_20170925.html"
}