{
	"id": "G5bM4O3FCIOaWWt",
	"json": "{\"id\":\"G5bM4O3FCIOaWWt\",\"url\":\"https://www.ntu.edu.tw/spotlight/2018/1432_20180525.html\",\"uniqueKey\":\"https://www.ntu.edu.tw/spotlight/2018/1432_20180525.html\",\"method\":\"GET\",\"noRetry\":false,\"retryCount\":0,\"errorMessages\":[],\"headers\":{},\"userData\":{\"__crawlee\":{\"enqueueStrategy\":\"same-hostname\"}}}",
	"method": "GET",
	"orderNo": 1741477576484,
	"retryCount": 0,
	"uniqueKey": "https://www.ntu.edu.tw/spotlight/2018/1432_20180525.html",
	"url": "https://www.ntu.edu.tw/spotlight/2018/1432_20180525.html"
}