{
	"id": "HRfJ6LWxNaSDD91",
	"json": "{\"id\":\"HRfJ6LWxNaSDD91\",\"url\":\"https://support.squarespace.com/hc/articles/8663316505997#h_01JFB321NVWFEFT95XF1KCH6ZV\",\"uniqueKey\":\"https://support.squarespace.com/hc/articles/8663316505997\",\"method\":\"GET\",\"noRetry\":false,\"retryCount\":0,\"errorMessages\":[],\"headers\":{},\"userData\":{\"__crawlee\":{\"enqueueStrategy\":\"same-hostname\"}}}",
	"method": "GET",
	"orderNo": 1741581578674,
	"retryCount": 0,
	"uniqueKey": "https://support.squarespace.com/hc/articles/8663316505997",
	"url": "https://support.squarespace.com/hc/articles/8663316505997#h_01JFB321NVWFEFT95XF1KCH6ZV"
}