{
	"id": "N922Z9jvkYHsdhp",
	"json": "{\"id\":\"N922Z9jvkYHsdhp\",\"url\":\"https://www.ntu.edu.tw/english/spotlight/2024/2275_20240529_1.jpg\",\"uniqueKey\":\"https://www.ntu.edu.tw/english/spotlight/2024/2275_20240529_1.jpg\",\"method\":\"GET\",\"noRetry\":false,\"retryCount\":0,\"errorMessages\":[],\"headers\":{},\"userData\":{\"__crawlee\":{\"enqueueStrategy\":\"same-hostname\"}}}",
	"method": "GET",
	"orderNo": 1741477617304,
	"retryCount": 0,
	"uniqueKey": "https://www.ntu.edu.tw/english/spotlight/2024/2275_20240529_1.jpg",
	"url": "https://www.ntu.edu.tw/english/spotlight/2024/2275_20240529_1.jpg"
}