{
	"id": "O1wGE4lLIaewUJd",
	"json": "{\"id\":\"O1wGE4lLIaewUJd\",\"url\":\"https://support.squarespace.com/hc/articles/360001280828\",\"uniqueKey\":\"https://support.squarespace.com/hc/articles/360001280828\",\"method\":\"GET\",\"noRetry\":false,\"retryCount\":0,\"errorMessages\":[],\"headers\":{},\"userData\":{\"__crawlee\":{\"enqueueStrategy\":\"same-hostname\"}}}",
	"method": "GET",
	"orderNo": 1741581587099,
	"retryCount": 0,
	"uniqueKey": "https://support.squarespace.com/hc/articles/360001280828",
	"url": "https://support.squarespace.com/hc/articles/360001280828"
}