{
	"id": "qGRBgt7v7wHp1RH",
	"json": "{\"id\":\"qGRBgt7v7wHp1RH\",\"url\":\"https://www.ntu.edu.tw/spotlight/2017/1289_20171205.html\",\"uniqueKey\":\"https://www.ntu.edu.tw/spotlight/2017/1289_20171205.html\",\"method\":\"GET\",\"noRetry\":false,\"retryCount\":0,\"errorMessages\":[],\"headers\":{},\"userData\":{\"__crawlee\":{\"enqueueStrategy\":\"same-hostname\"}}}",
	"method": "GET",
	"orderNo": 1741478261850,
	"retryCount": 0,
	"uniqueKey": "https://www.ntu.edu.tw/spotlight/2017/1289_20171205.html",
	"url": "https://www.ntu.edu.tw/spotlight/2017/1289_20171205.html"
}