{
	"id": "Qqi14goaVLN0DWZ",
	"json": "{\"id\":\"Qqi14goaVLN0DWZ\",\"url\":\"https://www.ntu.edu.tw/english/spotlight/2024/2239_20240306.html\",\"loadedUrl\":\"https://www.ntu.edu.tw/english/spotlight/2024/2239_20240306.html\",\"uniqueKey\":\"https://www.ntu.edu.tw/english/spotlight/2024/2239_20240306.html\",\"method\":\"GET\",\"noRetry\":false,\"retryCount\":0,\"errorMessages\":[],\"headers\":{},\"userData\":{\"__crawlee\":{\"enqueueStrategy\":\"same-hostname\",\"state\":4}},\"handledAt\":\"2025-03-08T23:47:02.242Z\"}",
	"method": "GET",
	"orderNo": null,
	"retryCount": 0,
	"uniqueKey": "https://www.ntu.edu.tw/english/spotlight/2024/2239_20240306.html",
	"url": "https://www.ntu.edu.tw/english/spotlight/2024/2239_20240306.html"
}