{
	"id": "R8pBPqXlxr1W1nn",
	"json": "{\"id\":\"R8pBPqXlxr1W1nn\",\"url\":\"https://www.ntu.edu.tw/spotlight/2021/1978_20210825.html\",\"uniqueKey\":\"https://www.ntu.edu.tw/spotlight/2021/1978_20210825.html\",\"method\":\"GET\",\"noRetry\":false,\"retryCount\":0,\"errorMessages\":[],\"headers\":{},\"userData\":{\"__crawlee\":{\"enqueueStrategy\":\"same-hostname\"}}}",
	"method": "GET",
	"orderNo": 1741478257503,
	"retryCount": 0,
	"uniqueKey": "https://www.ntu.edu.tw/spotlight/2021/1978_20210825.html",
	"url": "https://www.ntu.edu.tw/spotlight/2021/1978_20210825.html"
}