{
	"id": "xHG0iwufGUPX0Mw",
	"json": "{\"id\":\"xHG0iwufGUPX0Mw\",\"url\":\"https://www.ntu.edu.tw/spotlight/2020/1842_20200608.html\",\"uniqueKey\":\"https://www.ntu.edu.tw/spotlight/2020/1842_20200608.html\",\"method\":\"GET\",\"noRetry\":false,\"retryCount\":0,\"errorMessages\":[],\"headers\":{},\"userData\":{\"__crawlee\":{\"enqueueStrategy\":\"same-hostname\"}}}",
	"method": "GET",
	"orderNo": 1741477572186,
	"retryCount": 0,
	"uniqueKey": "https://www.ntu.edu.tw/spotlight/2020/1842_20200608.html",
	"url": "https://www.ntu.edu.tw/spotlight/2020/1842_20200608.html"
}