{
	"id": "yoFVSY0xCs2dvOa",
	"json": "{\"id\":\"yoFVSY0xCs2dvOa\",\"url\":\"https://support.squarespace.com/hc/articles/223016508\",\"uniqueKey\":\"https://support.squarespace.com/hc/articles/223016508\",\"method\":\"GET\",\"noRetry\":false,\"retryCount\":0,\"errorMessages\":[],\"headers\":{},\"userData\":{\"__crawlee\":{\"enqueueStrategy\":\"same-hostname\"}}}",
	"method": "GET",
	"orderNo": 1741581564982,
	"retryCount": 0,
	"uniqueKey": "https://support.squarespace.com/hc/articles/223016508",
	"url": "https://support.squarespace.com/hc/articles/223016508"
}