{
	"id": "Yu21aWONVJIXEuA",
	"json": "{\"id\":\"Yu21aWONVJIXEuA\",\"url\":\"https://www.ntu.edu.tw/english/spotlight/2017/1277_20171130.html\",\"uniqueKey\":\"https://www.ntu.edu.tw/english/spotlight/2017/1277_20171130.html\",\"method\":\"GET\",\"noRetry\":false,\"retryCount\":0,\"errorMessages\":[],\"headers\":{},\"userData\":{\"__crawlee\":{\"enqueueStrategy\":\"same-hostname\"}}}",
	"method": "GET",
	"orderNo": 1741477602129,
	"retryCount": 0,
	"uniqueKey": "https://www.ntu.edu.tw/english/spotlight/2017/1277_20171130.html",
	"url": "https://www.ntu.edu.tw/english/spotlight/2017/1277_20171130.html"
}